topftp/__init__.py
topftp/ftp.py
topftp-2024.9.13.dist-info/licenses/LICENSE.txt
topftp-2024.9.13.dist-info/METADATA
topftp-2024.9.13.dist-info/WHEEL
topftp-2024.9.13.dist-info/top_level.txt
topftp-2024.9.13.dist-info/RECORD
