Metadata-Version: 2.4
Name: topftp
Version: 2024.9.13
Summary: a package on top of ftplib to use FTP easily
Author-email: Lix Xu <xuzenglin@gmail.com>
License: BSD 3-Clause License
Project-URL: Homepage, https://github.com/lixxu/topftp
Project-URL: Bug Tracker, https://github.com/lixxu/topftp/issues
Keywords: ftp
Classifier: Programming Language :: Python :: 3
Classifier: License :: OSI Approved :: BSD License
Classifier: Operating System :: OS Independent
Requires-Python: >=3.6
License-File: LICENSE.txt
Dynamic: license-file
